puresnmp/__init__.py
puresnmp/adt.py
puresnmp/compatibility.py
puresnmp/const.py
puresnmp/credentials.py
puresnmp/exc.py
puresnmp/pdu.py
puresnmp/py.typed
puresnmp/transport.py
puresnmp/types.py
puresnmp/typevars.py
puresnmp/util.py
puresnmp/varbind.py
puresnmp/api/__init__.py
puresnmp/api/pythonic.py
puresnmp/api/raw.py
puresnmp/plugins/__init__.py
puresnmp/plugins/auth.py
puresnmp/plugins/mpm.py
puresnmp/plugins/pluginbase.py
puresnmp/plugins/priv.py
puresnmp/plugins/security.py
puresnmp_plugins/auth/hashbase.py
puresnmp_plugins/auth/md5.py
puresnmp_plugins/auth/sha1.py
puresnmp_plugins/mpm/v1.py
puresnmp_plugins/mpm/v2c.py
puresnmp_plugins/mpm/v2x.py
puresnmp_plugins/mpm/v3.py
puresnmp_plugins/priv/example.py
puresnmp_plugins/security/null.py
puresnmp_plugins/security/usm.py
puresnmp_plugins/security/v1.py
puresnmp_plugins/security/v2c.py
puresnmp-2.0.1.dist-info/LICENSE.txt
puresnmp-2.0.1.dist-info/METADATA
puresnmp-2.0.1.dist-info/WHEEL
puresnmp-2.0.1.dist-info/top_level.txt
puresnmp-2.0.1.dist-info/RECORD
