Metadata-Version: 2.1
Name: puresnmp
Version: 2.0.1
Summary: Pure Python SNMP implementation
Author-email: Michel Albert <michel@albert.lu>, POST Luxembourg <opensource@post.lu>
License: MIT
Project-URL: Homepage, https://github.com/exhuma/puresnmp
Project-URL: Bug Tracker, https://github.com/exhuma/puresnmp/issues
Project-URL: Repository, https://github.com/exhuma/puresnmp
Keywords: networking,snmp
Classifier: Development Status :: 5 - Production/Stable
Classifier: Intended Audience :: Developers
Classifier: Intended Audience :: System Administrators
Classifier: License :: OSI Approved :: MIT License
Classifier: Operating System :: OS Independent
Classifier: Programming Language :: Python
Classifier: Programming Language :: Python :: 3
Classifier: Topic :: System :: Networking
Classifier: Topic :: System :: Networking :: Monitoring
Classifier: Topic :: System :: Systems Administration
Requires-Python: >=3.6
License-File: LICENSE.txt
Requires-Dist: dataclasses; python_version < "3.7"
Requires-Dist: importlib_metadata; python_version < "3.8"
Requires-Dist: typing_extensions; python_version < "3.8"
Requires-Dist: x690<2.0,>=1.0
Provides-Extra: readthedocs
Requires-Dist: fabric; extra == "readthedocs"
Provides-Extra: crypto
Requires-Dist: puresnmp-crypto>=1.0.1; extra == "crypto"
Provides-Extra: dev
Requires-Dist: asyncmock; python_version < "3.8" and extra == "dev"
Requires-Dist: black>=20.8b1; extra == "dev"
Requires-Dist: fabric>=2.6.0; extra == "dev"
Requires-Dist: furo; extra == "dev"
Requires-Dist: mypy; extra == "dev"
Requires-Dist: pylint; extra == "dev"
Requires-Dist: pytest; extra == "dev"
Requires-Dist: pytest-asyncio; extra == "dev"
Requires-Dist: pytest-cov; extra == "dev"
Requires-Dist: pytest-dependency; extra == "dev"
Requires-Dist: sphinx; extra == "dev"
Requires-Dist: types-dataclasses; extra == "dev"
